LICENSE
README.md
setup.py
micropython_sram.egg-info/PKG-INFO
micropython_sram.egg-info/SOURCES.txt
micropython_sram.egg-info/dependency_links.txt
micropython_sram.egg-info/top_level.txt
sram/__init__.py
sram/sram23lcv1024.py